pipium_connect/__init__.py
pipium_connect/connect.py
pipium_connect/connect_options_model.py
pipium_connect/input_model.py
pipium_connect/model_model.py
pipium_connect/observer_model.py
pipium_connect/output_model.py
pipium_connect/previous_value_model.py
pipium_connect/rate_limit_model.py
pipium_connect/types_model.py
pipium_connect/widget_config_model.py
pipium_connect/widgets_model.py
pipium_connect-0.0.6.dist-info/METADATA
pipium_connect-0.0.6.dist-info/WHEEL
pipium_connect-0.0.6.dist-info/top_level.txt
pipium_connect-0.0.6.dist-info/RECORD
