Metadata-Version: 2.1
Name: pipium_connect
Version: 0.0.6
Summary: Pipium Python client that connects your code to the Pipium platform.
Author-email: Albin Berglund <e.a.e.berglund@gmail.com>
Requires-Python: >=3.7
Requires-Dist: python-socketio[client]==5.11.4
Requires-Dist: requests==2.32.3
